<Properties GitUserInfo="UsingGIT" StartupConfiguration="{32C3BDE6-E125-3128-82C1-25D0441455A3}|">
  <MonoDevelop.Ide.Workbench>
    <Files>
      <File FileName="Assets/Scripts/Laser.cs" Line="74" Column="24" />
      <File FileName="Assets/Scripts/SpawnManager.cs" />
      <File FileName="Assets/Scripts/Powerup.cs" />
      <File FileName="Assets/Scripts/GameManager.cs" Line="21" Column="32" />
      <File FileName="Assets/Scripts/Asteroid.cs" />
      <File FileName="Assets/Scripts/Enemy.cs" />
      <File FileName="Assets/Scripts/Explosion.cs" />
      <File FileName="Assets/Scripts/Player.cs" />
    </Files>
    <Pads>
      <Pad Id="ProjectPad">
        <State name="__root__">
          <Node name="My project" expanded="True">
            <Node name="Assets" expanded="True" selected="True">
              <Node name="Scripts" expanded="True">
                <Node name="Main_Menu" expanded="True" />
              </Node>
            </Node>
          </Node>
        </State>
      </Pad>
    </Pads>
  </MonoDevelop.Ide.Workbench>
  <MonoDevelop.Ide.DebuggingService.PinnedWatches />
  <MonoDevelop.Ide.Workspace ActiveConfiguration="Debug" />
  <MonoDevelop.Ide.ItemProperties.Assembly-CSharp PreferredExecutionTarget="24c54845-884e-4c09-bf92-c0344fe4c802" />
  <MonoDevelop.Ide.DebuggingService.Breakpoints>
    <BreakpointStore />
  </MonoDevelop.Ide.DebuggingService.Breakpoints>
  <MultiItemStartupConfigurations />
</Properties>